LICENSE
MANIFEST.in
README.md
setup.py
tox.ini
notmuch2/__init__.py
notmuch2/_base.py
notmuch2/_build.py
notmuch2/_config.py
notmuch2/_database.py
notmuch2/_errors.py
notmuch2/_message.py
notmuch2/_query.py
notmuch2/_tags.py
notmuch2/_thread.py
notmuch2.egg-info/PKG-INFO
notmuch2.egg-info/SOURCES.txt
notmuch2.egg-info/dependency_links.txt
notmuch2.egg-info/requires.txt
notmuch2.egg-info/top_level.txt
tests/test_base.py
tests/test_config.py
tests/test_database.py
tests/test_errors.py
tests/test_message.py
tests/test_tags.py
tests/test_thread.py