Metadata-Version: 2.4
Name: notmuch2
Version: 0.34.2
Summary: Pythonic bindings for the notmuch mail database using CFFI
Home-page: https://github.com/weilbith/notmuch2-python-bindings.git
Author: Floris Bruynooghe, Thore Weilbier
Author-email: flub@devork.be, thore@weilbier.net
License: GPL-3.0
Classifier: Development Status :: 3 - Alpha
Classifier: Intended Audience :: Developers
Classifier: License :: OSI Approved :: GNU General Public License (GPL)
Classifier: Programming Language :: Python :: 3
Classifier: Topic :: Communications :: Email
Classifier: Topic :: Software Development :: Libraries
License-File: LICENSE
Requires-Dist: cffi>=1.0.0
Dynamic: author
Dynamic: author-email
Dynamic: classifier
Dynamic: description
Dynamic: description-content-type
Dynamic: home-page
Dynamic: license
Dynamic: license-file
Dynamic: requires-dist
Dynamic: summary
